flet_pdfview/__init__.py
flet_pdfview/main.py
flet_pdfview-0.1.2.dist-info/METADATA
flet_pdfview-0.1.2.dist-info/WHEEL
flet_pdfview-0.1.2.dist-info/top_level.txt
flet_pdfview-0.1.2.dist-info/RECORD
