Metadata-Version: 2.4
Name: flet_pdfview
Version: 0.1.2
Summary: Flet pdf view for all platforms
Author: Mostafa Kessassi
Author-email: mustaphakessassi76@gmail.com
Requires-Python: >=3.10
Requires-Dist: asyncio
Requires-Dist: flet<=0.80.5
Requires-Dist: pymupdf
Dynamic: author
Dynamic: author-email
Dynamic: description
Dynamic: description-content-type
Dynamic: requires-dist
Dynamic: requires-python
Dynamic: summary
